sp_tjsp_divadmin/__init__.py
sp_tjsp_divadmin/my_driver.py
sp_tjsp_divadmin/my_functions.py
sp_tjsp_divadmin/my_paths.py
sp_tjsp_divadmin/data/output/geo/sp_tjsp_divadmin.7z
sp_tjsp_divadmin-0.0.14.dist-info/LICENSE
sp_tjsp_divadmin-0.0.14.dist-info/METADATA
sp_tjsp_divadmin-0.0.14.dist-info/WHEEL
sp_tjsp_divadmin-0.0.14.dist-info/top_level.txt
sp_tjsp_divadmin-0.0.14.dist-info/RECORD
