Metadata-Version: 2.2
Name: sp_tjsp_divadmin
Version: 0.0.14
Summary: Divisão Administrativa do TJSP, incluindo Comarcas, Cirscunscrições Judiciárias e Regiões Administrativas Judiciárias
Home-page: https://github.com/open-geodata/sp_tjsp_divadmin
Author: Michel Metran
Author-email: michelmetran@gmail.com
Keywords: python,dados espaciais,geoprocessamento
Classifier: Programming Language :: Python :: 3
Classifier: License :: OSI Approved :: MIT License
Classifier: Operating System :: OS Independent
Classifier: Natural Language :: Portuguese
Classifier: Intended Audience :: Developers
Requires-Python: >=3
License-File: LICENSE
Dynamic: author
Dynamic: author-email
Dynamic: classifier
Dynamic: description
Dynamic: description-content-type
Dynamic: home-page
Dynamic: keywords
Dynamic: requires-python
Dynamic: summary
